swiftbarmenu/__init__.py
swiftbarmenu/configuration.py
swiftbarmenu/menu.py
swiftbarmenu/notification.py
swiftbarmenu/persistence.py
swiftbarmenu/py.typed
swiftbarmenu-0.1.7.dist-info/METADATA
swiftbarmenu-0.1.7.dist-info/WHEEL
swiftbarmenu-0.1.7.dist-info/licenses/LICENSE
swiftbarmenu-0.1.7.dist-info/RECORD
