Metadata-Version: 2.4
Name: swiftbarmenu
Version: 0.1.7
Summary: Easy menu building for SwiftBar (... and xbar)
Project-URL: homepage, https://github.com/sdelquin/swiftbarmenu
Project-URL: repository, https://github.com/sdelquin/swiftbarmenu
Project-URL: issues, https://github.com/sdelquin/swiftbarmenu/issues
Author-email: Sergio Delgado Quintero <sdelquin@gmail.com>
Maintainer-email: Sergio Delgado Quintero <sdelquin@gmail.com>
License-Expression: MIT
License-File: LICENSE
Classifier: License :: OSI Approved :: MIT License
Classifier: Operating System :: OS Independent
Classifier: Programming Language :: Python :: 3
Requires-Python: >=3.9
